normcap/__init__.py
normcap/__main__.py
normcap/app.py
normcap/utils.py
normcap/clipboard/__init__.py
normcap/clipboard/main.py
normcap/clipboard/models.py
normcap/clipboard/system_info.py
normcap/clipboard/handlers/__init__.py
normcap/clipboard/handlers/pbcopy.py
normcap/clipboard/handlers/qtclipboard.py
normcap/clipboard/handlers/windll.py
normcap/clipboard/handlers/wlclipboard.py
normcap/clipboard/handlers/xclip.py
normcap/clipboard/handlers/xsel.py
normcap/detection/__init__.py
normcap/detection/detector.py
normcap/detection/models.py
normcap/detection/codes/__init__.py
normcap/detection/codes/detector.py
normcap/detection/codes/models.py
normcap/detection/ocr/__init__.py
normcap/detection/ocr/enhance.py
normcap/detection/ocr/models.py
normcap/detection/ocr/recognize.py
normcap/detection/ocr/tesseract.py
normcap/detection/ocr/transformer.py
normcap/detection/ocr/transformers/__init__.py
normcap/detection/ocr/transformers/email_address.py
normcap/detection/ocr/transformers/multi_line.py
normcap/detection/ocr/transformers/paragraph.py
normcap/detection/ocr/transformers/single_line.py
normcap/detection/ocr/transformers/url.py
normcap/detection/ocr/transformers/url_tlds.py
normcap/gui/__init__.py
normcap/gui/constants.py
normcap/gui/downloader.py
normcap/gui/introduction.py
normcap/gui/language_manager.py
normcap/gui/loading_indicator.py
normcap/gui/localization.py
normcap/gui/menu_button.py
normcap/gui/models.py
normcap/gui/notification_utils.py
normcap/gui/permissions_dialog.py
normcap/gui/resources.py
normcap/gui/settings.py
normcap/gui/system_info.py
normcap/gui/tray.py
normcap/gui/update_check.py
normcap/gui/utils.py
normcap/gui/wayland_dialog.py
normcap/gui/window.py
normcap/notification/__init__.py
normcap/notification/main.py
normcap/notification/models.py
normcap/notification/handlers/__init__.py
normcap/notification/handlers/dbus_portal.py
normcap/notification/handlers/notify_send.py
normcap/notification/handlers/qt.py
normcap/positioning/__init__.py
normcap-0.6.0.dist-info/METADATA
normcap-0.6.0.dist-info/WHEEL
normcap-0.6.0.dist-info/entry_points.txt
normcap-0.6.0.dist-info/licenses/LICENSE
normcap-0.6.0.dist-info/RECORD
