Metadata-Version: 2.4
Name: normcap
Version: 0.6.0
Summary: OCR-powered screen-capture tool to capture information instead of images.
Project-URL: Homepage, https://dynobo.github.io/normcap/
Project-URL: Issues, https://github.com/dynobo/normcap/issues
Project-URL: Source Code, https://github.com/dynobo/normcap
Project-URL: FAQs, https://dynobo.github.io/normcap/#faqs
Project-URL: Changelog, https://github.com/dynobo/normcap/blob/main/CHANGELOG
Project-URL: BuyMeACoffee, https://www.buymeacoffee.com/dynobo
Author-email: dynobo <dynobo@mailbox.org>
License: 
License-File: LICENSE
Keywords: capture,clipboard,ocr,screenshot
Classifier: Development Status :: 4 - Beta
Classifier: Intended Audience :: End Users/Desktop
Classifier: License :: OSI Approved :: GNU General Public License v3 (GPLv3)
Classifier: Operating System :: MacOS
Classifier: Operating System :: Microsoft :: Windows
Classifier: Operating System :: POSIX :: Linux
Classifier: Programming Language :: Python
Classifier: Programming Language :: Python :: 3.9
Classifier: Programming Language :: Python :: 3.10
Classifier: Programming Language :: Python :: 3.11
Classifier: Programming Language :: Python :: 3.12
Classifier: Programming Language :: Python :: Implementation :: CPython
Classifier: Topic :: Multimedia :: Graphics :: Capture :: Screen Capture
Classifier: Topic :: Utilities
Requires-Python: >=3.9
Requires-Dist: jeepney==0.9.0
Requires-Dist: pyside6-essentials==6.9.2
Requires-Dist: shiboken6==6.9.2
Requires-Dist: zxing-cpp==2.3.0
Provides-Extra: build
Requires-Dist: babel; extra == 'build'
Requires-Dist: toml; extra == 'build'
